{
    "Ar36": {
        "error": 9.837406450872877e-05,
        "error_type": "SEM",
        "filter_outliers_dict": {
            "filter_outliers": true,
            "iterations": 2,
            "std_devs": 2
        },
        "fit": "linear",
        "value": 0.0012650490681077597
    },
    "Ar37": {
        "error": 0.020257424357928447,
        "error_type": "SEM",
        "filter_outliers_dict": {
            "filter_outliers": true,
            "iterations": 2,
            "std_devs": 2
        },
        "fit": "linear",
        "value": 0.011323285226395209
    },
    "Ar38": {
        "error": 0.006687803577306448,
        "error_type": "SEM",
        "filter_outliers_dict": {
            "filter_outliers": true,
            "iterations": 2,
            "std_devs": 2
        },
        "fit": "linear",
        "value": -0.037846627377823905
    },
    "Ar39": {
        "error": 0.0014971753196177783,
        "error_type": "SEM",
        "filter_outliers_dict": {
            "filter_outliers": true,
            "iterations": 2,
            "std_devs": 2
        },
        "fit": "linear",
        "value": 0.607741489699591
    },
    "Ar40": {
        "error": 0.028219619997834247,
        "error_type": "SEM",
        "filter_outliers_dict": {
            "filter_outliers": true,
            "iterations": 2,
            "std_devs": 2
        },
        "fit": "linear",
        "value": 110.43975270121247
    }
}